.gitignore
CHANGES.txt
CONTRIBUTORS.txt
MANIFEST.in
README.rst
setup.py
docs/LICENSE.GPL
docs/LICENSE.txt
docs/MANUAL.txt
src/raptus/__init__.py
src/raptus.article.contents.egg-info/PKG-INFO
src/raptus.article.contents.egg-info/SOURCES.txt
src/raptus.article.contents.egg-info/dependency_links.txt
src/raptus.article.contents.egg-info/entry_points.txt
src/raptus.article.contents.egg-info/namespace_packages.txt
src/raptus.article.contents.egg-info/not-zip-safe
src/raptus.article.contents.egg-info/requires.txt
src/raptus.article.contents.egg-info/top_level.txt
src/raptus/article/__init__.py
src/raptus/article/contents/__init__.py
src/raptus/article/contents/configure.zcml
src/raptus/article/contents/browser/__init__.py
src/raptus/article/contents/browser/configure.zcml
src/raptus/article/contents/browser/contents.gif
src/raptus/article/contents/browser/contents.py
src/raptus/article/contents/i18n/raptus.article-de.mo
src/raptus/article/contents/i18n/raptus.article-de.po
src/raptus/article/contents/i18n/raptus.article.pot
src/raptus/article/contents/profiles/default/metadata.xml
src/raptus/article/contents/profiles/default/propertiestool.xml
src/raptus/article/contents/profiles/default/viewlets.xml