Metadata-Version: 1.1
Name: raptus.article.contents
Version: 1.0a1
Summary: Provides a simple article listing (table of contents)
Home-page: http://github.com/Raptus/raptus.article.contents
Author: Raptus AG
Author-email: dev@raptus.com
License: gpl
Platform: UNKNOWN
Classifier: Programming Language :: Python
